{
    "entries": [
        {
            "account_name": "mike",
            "rank": 1,
            "top_hero_ids": [],
            "badge_level": null
        },
        {
            "account_name": "s",
            "rank": 2,
            "top_hero_ids": [],
            "badge_level": null
        },
        {
            "account_name": "Dash",
            "rank": 3,
            "top_hero_ids": [],
            "badge_level": null
        },
        {
            "account_name": "Flawless",
            "rank": 4,
            "top_hero_ids": [],
            "badge_level": null
        },
        {
            "account_name": "CARNAL BEAST FLESH DESIRES",
            "rank": 5,
            "top_hero_ids": [],
            "badge_level": null
        },
        {
            "account_name": "Jarate",
            "rank": 6,
            "top_hero_ids": [],
            "badge_level": null
        },
        {
            "account_name": "Wanlead",
            "rank": 7,
            "top_hero_ids": [],
            "badge_level": null
        },
        {
            "account_name": "Konquer",
            "rank": 8,
            "top_hero_ids": [],
            "badge_level": null
        },
        {
            "account_name": "zsplor",
            "rank": 9,
            "top_hero_ids": [],
            "badge_level": null
        },
        {
            "account_name": "Dashboarrd",
            "rank": 10,
            "top_hero_ids": [],
            "badge_level": null
        },
        {
            "account_name": "Tabnyaa \u2665",
            "rank": 11,
            "top_hero_ids": [],
            "badge_level": null
        },
        {
            "account_name": "Presence",
            "rank": 12,
            "top_hero_ids": [],
            "badge_level": null
        },
        {
            "account_name": "Hip Shoulder Separation",
            "rank": 13,
            "top_hero_ids": [],
            "badge_level": null
        },
        {
            "account_name": "trash",
            "rank": 14,
            "top_hero_ids": [],
            "badge_level": null
        },
        {
            "account_name": "Furarc",
            "rank": 15,
            "top_hero_ids": [],
            "badge_level": null
        },
        {
            "account_name": "moyasu \u2601",
            "rank": 16,
            "top_hero_ids": [],
            "badge_level": null
        },
        {
            "account_name": "Full Synchro",
            "rank": 17,
            "top_hero_ids": [],
            "badge_level": null
        },
        {
            "account_name": "large (buoyant) seal",
            "rank": 18,
            "top_hero_ids": [],
            "badge_level": null
        },
        {
            "account_name": "GenericEdBoi on Twitch",
            "rank": 18,
            "top_hero_ids": [],
            "badge_level": null
        },
        {
            "account_name": "tv/JerryDeadlock",
            "rank": 20,
            "top_hero_ids": [],
            "badge_level": null
        },
        {
            "account_name": "Hdheggs",
            "rank": 21,
            "top_hero_ids": [],
            "badge_level": null
        },
        {
            "account_name": "tcibz",
            "rank": 22,
            "top_hero_ids": [],
            "badge_level": null
        },
        {
            "account_name": "Shimpy Man",
            "rank": 23,
            "top_hero_ids": [],
            "badge_level": null
        },
        {
            "account_name": "Dusa",
            "rank": 24,
            "top_hero_ids": [],
            "badge_level": null
        },
        {
            "account_name": "berry boy",
            "rank": 25,
            "top_hero_ids": [],
            "badge_level": null
        },
        {
            "account_name": "Q",
            "rank": 26,
            "top_hero_ids": [],
            "badge_level": null
        },
        {
            "account_name": "skrilly willy",
            "rank": 27,
            "top_hero_ids": [],
            "badge_level": null
        },
        {
            "account_name": "M1k3y",
            "rank": 28,
            "top_hero_ids": [],
            "badge_level": null
        },
        {
            "account_name": "I Love Vee",
            "rank": 29,
            "top_hero_ids": [],
            "badge_level": null
        },
        {
            "account_name": ".",
            "rank": 30,
            "top_hero_ids": [],
            "badge_level": null
        },
        {
            "account_name": "zealousduck",
            "rank": 31,
            "top_hero_ids": [],
            "badge_level": null
        },
        {
            "account_name": "Incon",
            "rank": 32,
            "top_hero_ids": [],
            "badge_level": null
        },
        {
            "account_name": "Moody blues",
            "rank": 33,
            "top_hero_ids": [],
            "badge_level": null
        },
        {
            "account_name": "MaGiiK",
            "rank": 34,
            "top_hero_ids": [],
            "badge_level": null
        },
        {
            "account_name": "peercontent twitch VIP",
            "rank": 35,
            "top_hero_ids": [],
            "badge_level": null
        },
        {
            "account_name": "Katczinsky",
            "rank": 36,
            "top_hero_ids": [],
            "badge_level": null
        },
        {
            "account_name": "SuperLux",
            "rank": 37,
            "top_hero_ids": [],
            "badge_level": null
        },
        {
            "account_name": "Chico",
            "rank": 38,
            "top_hero_ids": [],
            "badge_level": null
        },
        {
            "account_name": "Rainer",
            "rank": 39,
            "top_hero_ids": [],
            "badge_level": null
        },
        {
            "account_name": "JUST PLAYING FOR FUN!XDDD",
            "rank": 40,
            "top_hero_ids": [],
            "badge_level": null
        },
        {
            "account_name": "Certified Jorker",
            "rank": 41,
            "top_hero_ids": [],
            "badge_level": null
        },
        {
            "account_name": "upsilon",
            "rank": 42,
            "top_hero_ids": [],
            "badge_level": null
        },
        {
            "account_name": "CheesyBlood",
            "rank": 43,
            "top_hero_ids": [],
            "badge_level": null
        },
        {
            "account_name": "velloh",
            "rank": 44,
            "top_hero_ids": [],
            "badge_level": null
        },
        {
            "account_name": "Ygilkt4",
            "rank": 44,
            "top_hero_ids": [],
            "badge_level": null
        },
        {
            "account_name": "suzuya",
            "rank": 46,
            "top_hero_ids": [],
            "badge_level": null
        },
        {
            "account_name": "goodnight haise",
            "rank": 47,
            "top_hero_ids": [],
            "badge_level": null
        },
        {
            "account_name": "White Tee Poison",
            "rank": 48,
            "top_hero_ids": [],
            "badge_level": null
        },
        {
            "account_name": "twitch.tv/aZ_05",
            "rank": 49,
            "top_hero_ids": [],
            "badge_level": null
        },
        {
            "account_name": "Lad",
            "rank": 50,
            "top_hero_ids": [],
            "badge_level": null
        },
        {
            "account_name": "Alucard",
            "rank": 51,
            "top_hero_ids": [],
            "badge_level": null
        },
        {
            "account_name": "JRod",
            "rank": 52,
            "top_hero_ids": [],
            "badge_level": null
        },
        {
            "account_name": "CookiesNMilk",
            "rank": 53,
            "top_hero_ids": [],
            "badge_level": null
        },
        {
            "account_name": "ucantridewimmie",
            "rank": 54,
            "top_hero_ids": [],
            "badge_level": null
        },
        {
            "account_name": "Zwampy",
            "rank": 55,
            "top_hero_ids": [],
            "badge_level": null
        },
        {
            "account_name": "incorrigible stain",
            "rank": 56,
            "top_hero_ids": [],
            "badge_level": null
        },
        {
            "account_name": "Blazer",
            "rank": 57,
            "top_hero_ids": [],
            "badge_level": null
        },
        {
            "account_name": "Woed",
            "rank": 58,
            "top_hero_ids": [],
            "badge_level": null
        },
        {
            "account_name": "Shromo",
            "rank": 59,
            "top_hero_ids": [],
            "badge_level": null
        },
        {
            "account_name": "JungleBeanr",
            "rank": 60,
            "top_hero_ids": [],
            "badge_level": null
        },
        {
            "account_name": "Botryx",
            "rank": 60,
            "top_hero_ids": [],
            "badge_level": null
        },
        {
            "account_name": "dj",
            "rank": 62,
            "top_hero_ids": [],
            "badge_level": null
        },
        {
            "account_name": "leeneal66621",
            "rank": 63,
            "top_hero_ids": [],
            "badge_level": null
        },
        {
            "account_name": "Duhvided",
            "rank": 64,
            "top_hero_ids": [],
            "badge_level": null
        },
        {
            "account_name": "Tee",
            "rank": 65,
            "top_hero_ids": [],
            "badge_level": null
        },
        {
            "account_name": "johnny",
            "rank": 66,
            "top_hero_ids": [],
            "badge_level": null
        },
        {
            "account_name": "KayleIsCutie",
            "rank": 67,
            "top_hero_ids": [],
            "badge_level": null
        },
        {
            "account_name": "\u2605hurb!\u2605",
            "rank": 68,
            "top_hero_ids": [],
            "badge_level": null
        },
        {
            "account_name": "MrJeff88",
            "rank": 69,
            "top_hero_ids": [],
            "badge_level": null
        },
        {
            "account_name": "Offspec",
            "rank": 70,
            "top_hero_ids": [],
            "badge_level": null
        },
        {
            "account_name": "Griff2",
            "rank": 70,
            "top_hero_ids": [],
            "badge_level": null
        },
        {
            "account_name": "L U G O",
            "rank": 72,
            "top_hero_ids": [],
            "badge_level": null
        },
        {
            "account_name": "Raijin",
            "rank": 73,
            "top_hero_ids": [],
            "badge_level": null
        },
        {
            "account_name": "IP",
            "rank": 74,
            "top_hero_ids": [],
            "badge_level": null
        },
        {
            "account_name": "Depression49",
            "rank": 75,
            "top_hero_ids": [],
            "badge_level": null
        },
        {
            "account_name": "ToasterOvenJr",
            "rank": 75,
            "top_hero_ids": [],
            "badge_level": null
        },
        {
            "account_name": "Pokey",
            "rank": 77,
            "top_hero_ids": [],
            "badge_level": null
        },
        {
            "account_name": "bearrrrrrrry",
            "rank": 78,
            "top_hero_ids": [],
            "badge_level": null
        },
        {
            "account_name": "Calcium",
            "rank": 78,
            "top_hero_ids": [],
            "badge_level": null
        },
        {
            "account_name": "Eternity",
            "rank": 80,
            "top_hero_ids": [],
            "badge_level": null
        },
        {
            "account_name": "elaglo",
            "rank": 81,
            "top_hero_ids": [],
            "badge_level": null
        },
        {
            "account_name": "John Deadlock",
            "rank": 81,
            "top_hero_ids": [],
            "badge_level": null
        },
        {
            "account_name": "DerangedParadox",
            "rank": 83,
            "top_hero_ids": [],
            "badge_level": null
        },
        {
            "account_name": "JASON!",
            "rank": 84,
            "top_hero_ids": [],
            "badge_level": null
        },
        {
            "account_name": "Chubbs",
            "rank": 85,
            "top_hero_ids": [],
            "badge_level": null
        },
        {
            "account_name": "deadlock gumayusi",
            "rank": 85,
            "top_hero_ids": [],
            "badge_level": null
        },
        {
            "account_name": "Girny",
            "rank": 87,
            "top_hero_ids": [],
            "badge_level": null
        },
        {
            "account_name": "Platinum Puller",
            "rank": 88,
            "top_hero_ids": [],
            "badge_level": null
        },
        {
            "account_name": "Hankismagic",
            "rank": 89,
            "top_hero_ids": [],
            "badge_level": null
        },
        {
            "account_name": "Retro",
            "rank": 90,
            "top_hero_ids": [],
            "badge_level": null
        },
        {
            "account_name": "Banshee",
            "rank": 91,
            "top_hero_ids": [],
            "badge_level": null
        },
        {
            "account_name": "Eternal_51",
            "rank": 91,
            "top_hero_ids": [],
            "badge_level": null
        },
        {
            "account_name": "Crabtor",
            "rank": 93,
            "top_hero_ids": [],
            "badge_level": null
        },
        {
            "account_name": "uSiN",
            "rank": 94,
            "top_hero_ids": [],
            "badge_level": null
        },
        {
            "account_name": "calvin",
            "rank": 95,
            "top_hero_ids": [],
            "badge_level": null
        },
        {
            "account_name": "Bjartskular8",
            "rank": 96,
            "top_hero_ids": [],
            "badge_level": null
        },
        {
            "account_name": "EyesOfThousand",
            "rank": 97,
            "top_hero_ids": [],
            "badge_level": null
        },
        {
            "account_name": "SHIBUYAMELTDOWN",
            "rank": 98,
            "top_hero_ids": [],
            "badge_level": null
        },
        {
            "account_name": "Sycal",
            "rank": 99,
            "top_hero_ids": [],
            "badge_level": null
        },
        {
            "account_name": "Polarick",
            "rank": 99,
            "top_hero_ids": [],
            "badge_level": null
        },
        {
            "account_name": "Consurge",
            "rank": 101,
            "top_hero_ids": [],
            "badge_level": null
        },
        {
            "account_name": "4skinThief69",
            "rank": 102,
            "top_hero_ids": [],
            "badge_level": null
        },
        {
            "account_name": "Miles",
            "rank": 103,
            "top_hero_ids": [],
            "badge_level": null
        },
        {
            "account_name": "KennySprang",
            "rank": 103,
            "top_hero_ids": [],
            "badge_level": null
        },
        {
            "account_name": "CptGorden",
            "rank": 105,
            "top_hero_ids": [],
            "badge_level": null
        },
        {
            "account_name": "VeilWalkers SOIREE",
            "rank": 106,
            "top_hero_ids": [],
            "badge_level": null
        },
        {
            "account_name": "GloriousOwnage",
            "rank": 107,
            "top_hero_ids": [],
            "badge_level": null
        },
        {
            "account_name": "Certified Himbo",
            "rank": 107,
            "top_hero_ids": [],
            "badge_level": null
        },
        {
            "account_name": "Gimblejam",
            "rank": 107,
            "top_hero_ids": [],
            "badge_level": null
        },
        {
            "account_name": "Mini Map Looker Atter",
            "rank": 110,
            "top_hero_ids": [],
            "badge_level": null
        },
        {
            "account_name": "Alfie",
            "rank": 111,
            "top_hero_ids": [],
            "badge_level": null
        },
        {
            "account_name": "PAPI",
            "rank": 112,
            "top_hero_ids": [],
            "badge_level": null
        },
        {
            "account_name": "Cybersneaks",
            "rank": 113,
            "top_hero_ids": [],
            "badge_level": null
        },
        {
            "account_name": "Chat noir",
            "rank": 114,
            "top_hero_ids": [],
            "badge_level": null
        },
        {
            "account_name": "Hierophant",
            "rank": 114,
            "top_hero_ids": [],
            "badge_level": null
        },
        {
            "account_name": "foolycl",
            "rank": 116,
            "top_hero_ids": [],
            "badge_level": null
        },
        {
            "account_name": "skeet",
            "rank": 117,
            "top_hero_ids": [],
            "badge_level": null
        },
        {
            "account_name": "metawe",
            "rank": 118,
            "top_hero_ids": [],
            "badge_level": null
        },
        {
            "account_name": "Mooncow",
            "rank": 119,
            "top_hero_ids": [],
            "badge_level": null
        },
        {
            "account_name": "angel",
            "rank": 119,
            "top_hero_ids": [],
            "badge_level": null
        },
        {
            "account_name": "Ranger",
            "rank": 121,
            "top_hero_ids": [],
            "badge_level": null
        },
        {
            "account_name": "lukaslfox",
            "rank": 122,
            "top_hero_ids": [],
            "badge_level": null
        },
        {
            "account_name": "chudlock",
            "rank": 123,
            "top_hero_ids": [],
            "badge_level": null
        },
        {
            "account_name": "Odd",
            "rank": 124,
            "top_hero_ids": [],
            "badge_level": null
        },
        {
            "account_name": "wtfismyteamdoing",
            "rank": 125,
            "top_hero_ids": [],
            "badge_level": null
        },
        {
            "account_name": "logan",
            "rank": 126,
            "top_hero_ids": [],
            "badge_level": null
        },
        {
            "account_name": "aughhh",
            "rank": 127,
            "top_hero_ids": [],
            "badge_level": null
        },
        {
            "account_name": "G1antAXE",
            "rank": 128,
            "top_hero_ids": [],
            "badge_level": null
        },
        {
            "account_name": "Otters",
            "rank": 129,
            "top_hero_ids": [],
            "badge_level": null
        },
        {
            "account_name": "BEEFGOBLIN",
            "rank": 129,
            "top_hero_ids": [],
            "badge_level": null
        },
        {
            "account_name": "Ant",
            "rank": 131,
            "top_hero_ids": [],
            "badge_level": null
        },
        {
            "account_name": "The Merciless",
            "rank": 131,
            "top_hero_ids": [],
            "badge_level": null
        },
        {
            "account_name": "lurkz",
            "rank": 133,
            "top_hero_ids": [],
            "badge_level": null
        },
        {
            "account_name": "Seoljin",
            "rank": 133,
            "top_hero_ids": [],
            "badge_level": null
        },
        {
            "account_name": "MrRice20",
            "rank": 135,
            "top_hero_ids": [],
            "badge_level": null
        },
        {
            "account_name": "yerf",
            "rank": 135,
            "top_hero_ids": [],
            "badge_level": null
        },
        {
            "account_name": "schaq",
            "rank": 135,
            "top_hero_ids": [],
            "badge_level": null
        },
        {
            "account_name": "869wizard",
            "rank": 138,
            "top_hero_ids": [],
            "badge_level": null
        },
        {
            "account_name": "BakeR [aeons]",
            "rank": 139,
            "top_hero_ids": [],
            "badge_level": null
        },
        {
            "account_name": "fork",
            "rank": 140,
            "top_hero_ids": [],
            "badge_level": null
        },
        {
            "account_name": "Azzidahaka",
            "rank": 140,
            "top_hero_ids": [],
            "badge_level": null
        },
        {
            "account_name": "Poptart From Mars",
            "rank": 142,
            "top_hero_ids": [],
            "badge_level": null
        },
        {
            "account_name": "griff3",
            "rank": 142,
            "top_hero_ids": [],
            "badge_level": null
        },
        {
            "account_name": "thesaurus",
            "rank": 144,
            "top_hero_ids": [],
            "badge_level": null
        },
        {
            "account_name": "Jango",
            "rank": 145,
            "top_hero_ids": [],
            "badge_level": null
        },
        {
            "account_name": "joie",
            "rank": 146,
            "top_hero_ids": [],
            "badge_level": null
        },
        {
            "account_name": "Yamato",
            "rank": 146,
            "top_hero_ids": [],
            "badge_level": null
        },
        {
            "account_name": "PigNamedTonyHawg",
            "rank": 146,
            "top_hero_ids": [],
            "badge_level": null
        },
        {
            "account_name": "Zarathaya",
            "rank": 149,
            "top_hero_ids": [],
            "badge_level": null
        },
        {
            "account_name": "Vendetta",
            "rank": 150,
            "top_hero_ids": [],
            "badge_level": null
        },
        {
            "account_name": "James",
            "rank": 151,
            "top_hero_ids": [],
            "badge_level": null
        },
        {
            "account_name": "OneTap",
            "rank": 152,
            "top_hero_ids": [],
            "badge_level": null
        },
        {
            "account_name": "Sprodmen",
            "rank": 153,
            "top_hero_ids": [],
            "badge_level": null
        },
        {
            "account_name": "SHAQ DIESL",
            "rank": 153,
            "top_hero_ids": [],
            "badge_level": null
        },
        {
            "account_name": "maxi",
            "rank": 155,
            "top_hero_ids": [],
            "badge_level": null
        },
        {
            "account_name": "Gromit",
            "rank": 155,
            "top_hero_ids": [],
            "badge_level": null
        },
        {
            "account_name": "Cow",
            "rank": 157,
            "top_hero_ids": [],
            "badge_level": null
        },
        {
            "account_name": "BigKitty69",
            "rank": 158,
            "top_hero_ids": [],
            "badge_level": null
        },
        {
            "account_name": "Tommy Pickles",
            "rank": 159,
            "top_hero_ids": [],
            "badge_level": null
        },
        {
            "account_name": "Va$$h.",
            "rank": 160,
            "top_hero_ids": [],
            "badge_level": null
        },
        {
            "account_name": "FataLz",
            "rank": 161,
            "top_hero_ids": [],
            "badge_level": null
        },
        {
            "account_name": "ShidCumFardPoo",
            "rank": 162,
            "top_hero_ids": [],
            "badge_level": null
        },
        {
            "account_name": "Negador",
            "rank": 163,
            "top_hero_ids": [],
            "badge_level": null
        },
        {
            "account_name": "ctc",
            "rank": 164,
            "top_hero_ids": [],
            "badge_level": null
        },
        {
            "account_name": "DoobyGooster",
            "rank": 165,
            "top_hero_ids": [],
            "badge_level": null
        },
        {
            "account_name": "maxz",
            "rank": 165,
            "top_hero_ids": [],
            "badge_level": null
        },
        {
            "account_name": "i'm beautiful IRL",
            "rank": 167,
            "top_hero_ids": [],
            "badge_level": null
        },
        {
            "account_name": "FirstWorldProblems",
            "rank": 168,
            "top_hero_ids": [],
            "badge_level": null
        },
        {
            "account_name": "pyourr",
            "rank": 169,
            "top_hero_ids": [],
            "badge_level": null
        },
        {
            "account_name": "AL\u00e3N",
            "rank": 170,
            "top_hero_ids": [],
            "badge_level": null
        },
        {
            "account_name": "Xual",
            "rank": 171,
            "top_hero_ids": [],
            "badge_level": null
        },
        {
            "account_name": "A blueberry",
            "rank": 172,
            "top_hero_ids": [],
            "badge_level": null
        },
        {
            "account_name": "Artefis",
            "rank": 173,
            "top_hero_ids": [],
            "badge_level": null
        },
        {
            "account_name": "PapaDart",
            "rank": 173,
            "top_hero_ids": [],
            "badge_level": null
        },
        {
            "account_name": "WardenRant",
            "rank": 175,
            "top_hero_ids": [],
            "badge_level": null
        },
        {
            "account_name": "DrewFos",
            "rank": 176,
            "top_hero_ids": [],
            "badge_level": null
        },
        {
            "account_name": "Elendil",
            "rank": 176,
            "top_hero_ids": [],
            "badge_level": null
        },
        {
            "account_name": "CrimeCommitter",
            "rank": 178,
            "top_hero_ids": [],
            "badge_level": null
        },
        {
            "account_name": "it ain't no homie",
            "rank": 179,
            "top_hero_ids": [],
            "badge_level": null
        },
        {
            "account_name": "Sean The Mahn",
            "rank": 180,
            "top_hero_ids": [],
            "badge_level": null
        },
        {
            "account_name": "Kopeschka_TwitchTV",
            "rank": 181,
            "top_hero_ids": [],
            "badge_level": null
        },
        {
            "account_name": "Akashii",
            "rank": 181,
            "top_hero_ids": [],
            "badge_level": null
        },
        {
            "account_name": "hzrd",
            "rank": 183,
            "top_hero_ids": [],
            "badge_level": null
        },
        {
            "account_name": "foreign49er",
            "rank": 184,
            "top_hero_ids": [],
            "badge_level": null
        },
        {
            "account_name": "HoldTheLine",
            "rank": 185,
            "top_hero_ids": [],
            "badge_level": null
        },
        {
            "account_name": "Snakeboot",
            "rank": 186,
            "top_hero_ids": [],
            "badge_level": null
        },
        {
            "account_name": "DaHubs901",
            "rank": 187,
            "top_hero_ids": [],
            "badge_level": null
        },
        {
            "account_name": "Yingas",
            "rank": 188,
            "top_hero_ids": [],
            "badge_level": null
        },
        {
            "account_name": "K",
            "rank": 188,
            "top_hero_ids": [],
            "badge_level": null
        },
        {
            "account_name": "RandomEpic",
            "rank": 190,
            "top_hero_ids": [],
            "badge_level": null
        },
        {
            "account_name": "fortnitelover762",
            "rank": 191,
            "top_hero_ids": [],
            "badge_level": null
        },
        {
            "account_name": "meekmillnfish",
            "rank": 191,
            "top_hero_ids": [],
            "badge_level": null
        },
        {
            "account_name": "Gear 10 Luffy",
            "rank": 193,
            "top_hero_ids": [],
            "badge_level": null
        },
        {
            "account_name": "Geneva",
            "rank": 193,
            "top_hero_ids": [],
            "badge_level": null
        },
        {
            "account_name": "culir58321",
            "rank": 195,
            "top_hero_ids": [],
            "badge_level": null
        },
        {
            "account_name": "Alli",
            "rank": 195,
            "top_hero_ids": [],
            "badge_level": null
        },
        {
            "account_name": "Aceclump",
            "rank": 195,
            "top_hero_ids": [],
            "badge_level": null
        },
        {
            "account_name": "Holy, Holy",
            "rank": 198,
            "top_hero_ids": [],
            "badge_level": null
        },
        {
            "account_name": "Grimsight",
            "rank": 199,
            "top_hero_ids": [],
            "badge_level": null
        },
        {
            "account_name": "StylonPylon",
            "rank": 199,
            "top_hero_ids": [],
            "badge_level": null
        },
        {
            "account_name": "Turd Ferguson",
            "rank": 201,
            "top_hero_ids": [],
            "badge_level": null
        },
        {
            "account_name": "Whamboozled",
            "rank": 202,
            "top_hero_ids": [],
            "badge_level": null
        },
        {
            "account_name": "Roll-Me-One Kenobi\u2122",
            "rank": 203,
            "top_hero_ids": [],
            "badge_level": null
        },
        {
            "account_name": "Falacia",
            "rank": 203,
            "top_hero_ids": [],
            "badge_level": null
        },
        {
            "account_name": "Bork",
            "rank": 205,
            "top_hero_ids": [],
            "badge_level": null
        },
        {
            "account_name": "Panionator",
            "rank": 206,
            "top_hero_ids": [],
            "badge_level": null
        },
        {
            "account_name": "Midnight",
            "rank": 206,
            "top_hero_ids": [],
            "badge_level": null
        },
        {
            "account_name": "Chisato Nishikigi",
            "rank": 208,
            "top_hero_ids": [],
            "badge_level": null
        },
        {
            "account_name": "Tnnobby",
            "rank": 208,
            "top_hero_ids": [],
            "badge_level": null
        },
        {
            "account_name": "SMelon",
            "rank": 210,
            "top_hero_ids": [],
            "badge_level": null
        },
        {
            "account_name": "madmerrick",
            "rank": 211,
            "top_hero_ids": [],
            "badge_level": null
        },
        {
            "account_name": "Trenk",
            "rank": 212,
            "top_hero_ids": [],
            "badge_level": null
        },
        {
            "account_name": "Zwitzansky",
            "rank": 213,
            "top_hero_ids": [],
            "badge_level": null
        },
        {
            "account_name": "Feral",
            "rank": 214,
            "top_hero_ids": [],
            "badge_level": null
        },
        {
            "account_name": "ScorchingRay",
            "rank": 215,
            "top_hero_ids": [],
            "badge_level": null
        },
        {
            "account_name": "fr-eyes",
            "rank": 216,
            "top_hero_ids": [],
            "badge_level": null
        },
        {
            "account_name": "shoop",
            "rank": 217,
            "top_hero_ids": [],
            "badge_level": null
        },
        {
            "account_name": "XxUcGamerxX",
            "rank": 218,
            "top_hero_ids": [],
            "badge_level": null
        },
        {
            "account_name": "aFatLootBag",
            "rank": 218,
            "top_hero_ids": [],
            "badge_level": null
        },
        {
            "account_name": "pootis",
            "rank": 220,
            "top_hero_ids": [],
            "badge_level": null
        },
        {
            "account_name": "Mugicha Maniac",
            "rank": 221,
            "top_hero_ids": [],
            "badge_level": null
        },
        {
            "account_name": "SOROS",
            "rank": 222,
            "top_hero_ids": [],
            "badge_level": null
        },
        {
            "account_name": "GoodTimez",
            "rank": 223,
            "top_hero_ids": [],
            "badge_level": null
        },
        {
            "account_name": "Ditters",
            "rank": 223,
            "top_hero_ids": [],
            "badge_level": null
        },
        {
            "account_name": "diglybick",
            "rank": 225,
            "top_hero_ids": [],
            "badge_level": null
        },
        {
            "account_name": "Juicer",
            "rank": 226,
            "top_hero_ids": [],
            "badge_level": null
        },
        {
            "account_name": "CAW CAW!!!! CAW CAW!!!!",
            "rank": 227,
            "top_hero_ids": [],
            "badge_level": null
        },
        {
            "account_name": "trigga",
            "rank": 227,
            "top_hero_ids": [],
            "badge_level": null
        },
        {
            "account_name": "mathwiz28",
            "rank": 229,
            "top_hero_ids": [],
            "badge_level": null
        },
        {
            "account_name": "L1tonator",
            "rank": 230,
            "top_hero_ids": [],
            "badge_level": null
        },
        {
            "account_name": "wassam",
            "rank": 231,
            "top_hero_ids": [],
            "badge_level": null
        },
        {
            "account_name": "[BS] Rock Lobster",
            "rank": 232,
            "top_hero_ids": [],
            "badge_level": null
        },
        {
            "account_name": "Chokolat\u30c4",
            "rank": 233,
            "top_hero_ids": [],
            "badge_level": null
        },
        {
            "account_name": "L0cksss",
            "rank": 234,
            "top_hero_ids": [],
            "badge_level": null
        },
        {
            "account_name": "Unbackedbird274",
            "rank": 235,
            "top_hero_ids": [],
            "badge_level": null
        },
        {
            "account_name": "Breadlock",
            "rank": 235,
            "top_hero_ids": [],
            "badge_level": null
        },
        {
            "account_name": "Tao",
            "rank": 237,
            "top_hero_ids": [],
            "badge_level": null
        },
        {
            "account_name": "hano",
            "rank": 238,
            "top_hero_ids": [],
            "badge_level": null
        },
        {
            "account_name": "Monke",
            "rank": 239,
            "top_hero_ids": [],
            "badge_level": null
        },
        {
            "account_name": "year of our lord gritty",
            "rank": 240,
            "top_hero_ids": [],
            "badge_level": null
        },
        {
            "account_name": "U-Type",
            "rank": 241,
            "top_hero_ids": [],
            "badge_level": null
        },
        {
            "account_name": "FTL",
            "rank": 242,
            "top_hero_ids": [],
            "badge_level": null
        },
        {
            "account_name": "Nicodemus Z",
            "rank": 242,
            "top_hero_ids": [],
            "badge_level": null
        },
        {
            "account_name": "BOT GENERAL \"CULON\" GARCIA",
            "rank": 244,
            "top_hero_ids": [],
            "badge_level": null
        },
        {
            "account_name": "Pioneer of Dawn",
            "rank": 245,
            "top_hero_ids": [],
            "badge_level": null
        },
        {
            "account_name": "DarkJava",
            "rank": 245,
            "top_hero_ids": [],
            "badge_level": null
        },
        {
            "account_name": "lopunny inflation enjoyer",
            "rank": 245,
            "top_hero_ids": [],
            "badge_level": null
        },
        {
            "account_name": "woman #57",
            "rank": 248,
            "top_hero_ids": [],
            "badge_level": null
        },
        {
            "account_name": "Holiday",
            "rank": 249,
            "top_hero_ids": [],
            "badge_level": null
        },
        {
            "account_name": "Pooop",
            "rank": 250,
            "top_hero_ids": [],
            "badge_level": null
        },
        {
            "account_name": "hdz",
            "rank": 251,
            "top_hero_ids": [],
            "badge_level": null
        },
        {
            "account_name": "YourGoodNeighbor",
            "rank": 252,
            "top_hero_ids": [],
            "badge_level": null
        },
        {
            "account_name": "Rexx",
            "rank": 253,
            "top_hero_ids": [],
            "badge_level": null
        },
        {
            "account_name": "Conchobhar",
            "rank": 253,
            "top_hero_ids": [],
            "badge_level": null
        },
        {
            "account_name": "cavern //",
            "rank": 253,
            "top_hero_ids": [],
            "badge_level": null
        },
        {
            "account_name": "CleeTorres",
            "rank": 256,
            "top_hero_ids": [],
            "badge_level": null
        },
        {
            "account_name": "Pyrocake",
            "rank": 257,
            "top_hero_ids": [],
            "badge_level": null
        },
        {
            "account_name": "nevergiveup!",
            "rank": 258,
            "top_hero_ids": [],
            "badge_level": null
        },
        {
            "account_name": "Drain Bamage",
            "rank": 259,
            "top_hero_ids": [],
            "badge_level": null
        },
        {
            "account_name": "swigbiscuit",
            "rank": 260,
            "top_hero_ids": [],
            "badge_level": null
        },
        {
            "account_name": "TheHerofTime",
            "rank": 261,
            "top_hero_ids": [],
            "badge_level": null
        },
        {
            "account_name": "blobman195",
            "rank": 261,
            "top_hero_ids": [],
            "badge_level": null
        },
        {
            "account_name": "Evalance",
            "rank": 263,
            "top_hero_ids": [],
            "badge_level": null
        },
        {
            "account_name": "KingErk",
            "rank": 264,
            "top_hero_ids": [],
            "badge_level": null
        },
        {
            "account_name": "Dafigs",
            "rank": 265,
            "top_hero_ids": [],
            "badge_level": null
        },
        {
            "account_name": "Darth",
            "rank": 265,
            "top_hero_ids": [],
            "badge_level": null
        },
        {
            "account_name": "Mild foot stroker",
            "rank": 265,
            "top_hero_ids": [],
            "badge_level": null
        },
        {
            "account_name": "filishot",
            "rank": 268,
            "top_hero_ids": [],
            "badge_level": null
        },
        {
            "account_name": "GOOSE",
            "rank": 268,
            "top_hero_ids": [],
            "badge_level": null
        },
        {
            "account_name": "yeeko",
            "rank": 270,
            "top_hero_ids": [],
            "badge_level": null
        },
        {
            "account_name": "JustAnotherBoo",
            "rank": 271,
            "top_hero_ids": [],
            "badge_level": null
        },
        {
            "account_name": "UnsightlyChip8",
            "rank": 272,
            "top_hero_ids": [],
            "badge_level": null
        },
        {
            "account_name": "rjlu",
            "rank": 273,
            "top_hero_ids": [],
            "badge_level": null
        },
        {
            "account_name": "yoube",
            "rank": 274,
            "top_hero_ids": [],
            "badge_level": null
        },
        {
            "account_name": "Dinkledoink",
            "rank": 275,
            "top_hero_ids": [],
            "badge_level": null
        },
        {
            "account_name": "Red Velvet",
            "rank": 276,
            "top_hero_ids": [],
            "badge_level": null
        },
        {
            "account_name": "G\u0247neralNick",
            "rank": 277,
            "top_hero_ids": [],
            "badge_level": null
        },
        {
            "account_name": "Typhon",
            "rank": 278,
            "top_hero_ids": [],
            "badge_level": null
        },
        {
            "account_name": "Sweyzaka",
            "rank": 279,
            "top_hero_ids": [],
            "badge_level": null
        },
        {
            "account_name": "Funny",
            "rank": 279,
            "top_hero_ids": [],
            "badge_level": null
        },
        {
            "account_name": "show piggies",
            "rank": 279,
            "top_hero_ids": [],
            "badge_level": null
        },
        {
            "account_name": "Kyras",
            "rank": 282,
            "top_hero_ids": [],
            "badge_level": null
        },
        {
            "account_name": "Day",
            "rank": 283,
            "top_hero_ids": [],
            "badge_level": null
        },
        {
            "account_name": "TTV ConfuzedPanda13",
            "rank": 284,
            "top_hero_ids": [],
            "badge_level": null
        },
        {
            "account_name": "idiot",
            "rank": 285,
            "top_hero_ids": [],
            "badge_level": null
        },
        {
            "account_name": "h-united-18",
            "rank": 286,
            "top_hero_ids": [],
            "badge_level": null
        },
        {
            "account_name": "Dann",
            "rank": 287,
            "top_hero_ids": [],
            "badge_level": null
        },
        {
            "account_name": "bingus",
            "rank": 288,
            "top_hero_ids": [],
            "badge_level": null
        },
        {
            "account_name": "Conifir",
            "rank": 288,
            "top_hero_ids": [],
            "badge_level": null
        },
        {
            "account_name": "z-z_z  DENY, DEFEND, DEPOSE",
            "rank": 290,
            "top_hero_ids": [],
            "badge_level": null
        },
        {
            "account_name": "BigPunLaFlare",
            "rank": 291,
            "top_hero_ids": [],
            "badge_level": null
        },
        {
            "account_name": "RavensOmen",
            "rank": 291,
            "top_hero_ids": [],
            "badge_level": null
        },
        {
            "account_name": "Ibuki Suika",
            "rank": 293,
            "top_hero_ids": [],
            "badge_level": null
        },
        {
            "account_name": "Power Nelson",
            "rank": 293,
            "top_hero_ids": [],
            "badge_level": null
        },
        {
            "account_name": "kachimaru",
            "rank": 295,
            "top_hero_ids": [],
            "badge_level": null
        },
        {
            "account_name": "Ghoulsrhot",
            "rank": 296,
            "top_hero_ids": [],
            "badge_level": null
        },
        {
            "account_name": "exceed",
            "rank": 297,
            "top_hero_ids": [],
            "badge_level": null
        },
        {
            "account_name": "Aranock",
            "rank": 298,
            "top_hero_ids": [],
            "badge_level": null
        },
        {
            "account_name": "[AWM]Tenzky",
            "rank": 299,
            "top_hero_ids": [],
            "badge_level": null
        },
        {
            "account_name": "zara",
            "rank": 300,
            "top_hero_ids": [],
            "badge_level": null
        },
        {
            "account_name": "kirnos",
            "rank": 301,
            "top_hero_ids": [],
            "badge_level": null
        },
        {
            "account_name": "muted",
            "rank": 301,
            "top_hero_ids": [],
            "badge_level": null
        },
        {
            "account_name": "halliday",
            "rank": 303,
            "top_hero_ids": [],
            "badge_level": null
        },
        {
            "account_name": "TrollOfJom",
            "rank": 304,
            "top_hero_ids": [],
            "badge_level": null
        },
        {
            "account_name": "Hephaestus",
            "rank": 305,
            "top_hero_ids": [],
            "badge_level": null
        },
        {
            "account_name": "- - Jehct",
            "rank": 306,
            "top_hero_ids": [],
            "badge_level": null
        },
        {
            "account_name": "ya jabooky",
            "rank": 306,
            "top_hero_ids": [],
            "badge_level": null
        },
        {
            "account_name": "Kakku",
            "rank": 308,
            "top_hero_ids": [],
            "badge_level": null
        },
        {
            "account_name": "Brobot75",
            "rank": 309,
            "top_hero_ids": [],
            "badge_level": null
        },
        {
            "account_name": "Glaze",
            "rank": 309,
            "top_hero_ids": [],
            "badge_level": null
        },
        {
            "account_name": "rhd16",
            "rank": 311,
            "top_hero_ids": [],
            "badge_level": null
        },
        {
            "account_name": "Two Ton Tony",
            "rank": 311,
            "top_hero_ids": [],
            "badge_level": null
        },
        {
            "account_name": "Zeus",
            "rank": 313,
            "top_hero_ids": [],
            "badge_level": null
        },
        {
            "account_name": "beaner bins and binky",
            "rank": 314,
            "top_hero_ids": [],
            "badge_level": null
        },
        {
            "account_name": "Stacaay",
            "rank": 314,
            "top_hero_ids": [],
            "badge_level": null
        },
        {
            "account_name": "Grace",
            "rank": 316,
            "top_hero_ids": [],
            "badge_level": null
        },
        {
            "account_name": "InKane",
            "rank": 317,
            "top_hero_ids": [],
            "badge_level": null
        },
        {
            "account_name": "ChandyMan",
            "rank": 318,
            "top_hero_ids": [],
            "badge_level": null
        },
        {
            "account_name": "Parker",
            "rank": 319,
            "top_hero_ids": [],
            "badge_level": null
        },
        {
            "account_name": "Booty Hunter",
            "rank": 320,
            "top_hero_ids": [],
            "badge_level": null
        },
        {
            "account_name": "Prost8popper",
            "rank": 320,
            "top_hero_ids": [],
            "badge_level": null
        },
        {
            "account_name": "m0ng0",
            "rank": 322,
            "top_hero_ids": [],
            "badge_level": null
        },
        {
            "account_name": "dollerama",
            "rank": 323,
            "top_hero_ids": [],
            "badge_level": null
        },
        {
            "account_name": "Gnole",
            "rank": 324,
            "top_hero_ids": [],
            "badge_level": null
        },
        {
            "account_name": "nerf vyper",
            "rank": 325,
            "top_hero_ids": [],
            "badge_level": null
        },
        {
            "account_name": "skrrt skrrt",
            "rank": 326,
            "top_hero_ids": [],
            "badge_level": null
        },
        {
            "account_name": "WithInClouds",
            "rank": 326,
            "top_hero_ids": [],
            "badge_level": null
        },
        {
            "account_name": "Atomsk099",
            "rank": 328,
            "top_hero_ids": [],
            "badge_level": null
        },
        {
            "account_name": "PAPA GATO",
            "rank": 329,
            "top_hero_ids": [],
            "badge_level": null
        },
        {
            "account_name": "Meisterschaft",
            "rank": 330,
            "top_hero_ids": [],
            "badge_level": null
        },
        {
            "account_name": "Timp",
            "rank": 330,
            "top_hero_ids": [],
            "badge_level": null
        },
        {
            "account_name": "snezze21",
            "rank": 332,
            "top_hero_ids": [],
            "badge_level": null
        },
        {
            "account_name": "saaf",
            "rank": 333,
            "top_hero_ids": [],
            "badge_level": null
        },
        {
            "account_name": "griff",
            "rank": 333,
            "top_hero_ids": [],
            "badge_level": null
        },
        {
            "account_name": "lightoodle",
            "rank": 335,
            "top_hero_ids": [],
            "badge_level": null
        },
        {
            "account_name": "\u0414\u0435\u0443\u0441 \u0412\u043e\u043b\u044c\u0442",
            "rank": 335,
            "top_hero_ids": [],
            "badge_level": null
        },
        {
            "account_name": "Ruk",
            "rank": 335,
            "top_hero_ids": [],
            "badge_level": null
        },
        {
            "account_name": "| iv1 |",
            "rank": 338,
            "top_hero_ids": [],
            "badge_level": null
        },
        {
            "account_name": "Sneaky J",
            "rank": 339,
            "top_hero_ids": [],
            "badge_level": null
        },
        {
            "account_name": "cdice",
            "rank": 340,
            "top_hero_ids": [],
            "badge_level": null
        },
        {
            "account_name": "marshmewwo",
            "rank": 340,
            "top_hero_ids": [],
            "badge_level": null
        },
        {
            "account_name": "8Whack",
            "rank": 342,
            "top_hero_ids": [],
            "badge_level": null
        },
        {
            "account_name": "SNAP CRACKLE POP",
            "rank": 343,
            "top_hero_ids": [],
            "badge_level": null
        },
        {
            "account_name": "jaK",
            "rank": 344,
            "top_hero_ids": [],
            "badge_level": null
        },
        {
            "account_name": "Chuckles",
            "rank": 345,
            "top_hero_ids": [],
            "badge_level": null
        },
        {
            "account_name": "Flippy1717",
            "rank": 345,
            "top_hero_ids": [],
            "badge_level": null
        },
        {
            "account_name": "Ur cute :3",
            "rank": 345,
            "top_hero_ids": [],
            "badge_level": null
        },
        {
            "account_name": "Cat Overlord",
            "rank": 348,
            "top_hero_ids": [],
            "badge_level": null
        },
        {
            "account_name": "ronin20181",
            "rank": 349,
            "top_hero_ids": [],
            "badge_level": null
        },
        {
            "account_name": "BarkXD",
            "rank": 350,
            "top_hero_ids": [],
            "badge_level": null
        },
        {
            "account_name": "zionjazz06",
            "rank": 350,
            "top_hero_ids": [],
            "badge_level": null
        },
        {
            "account_name": "Dobby",
            "rank": 352,
            "top_hero_ids": [],
            "badge_level": null
        },
        {
            "account_name": "Reverie",
            "rank": 353,
            "top_hero_ids": [],
            "badge_level": null
        },
        {
            "account_name": "Artic",
            "rank": 354,
            "top_hero_ids": [],
            "badge_level": null
        },
        {
            "account_name": "ReyNetic",
            "rank": 354,
            "top_hero_ids": [],
            "badge_level": null
        },
        {
            "account_name": "SteadyMetal0623",
            "rank": 356,
            "top_hero_ids": [],
            "badge_level": null
        },
        {
            "account_name": "BuckMeister15_TTV",
            "rank": 356,
            "top_hero_ids": [],
            "badge_level": null
        },
        {
            "account_name": "starfudger",
            "rank": 358,
            "top_hero_ids": [],
            "badge_level": null
        },
        {
            "account_name": "Krispy",
            "rank": 359,
            "top_hero_ids": [],
            "badge_level": null
        },
        {
            "account_name": "ShortyKills",
            "rank": 360,
            "top_hero_ids": [],
            "badge_level": null
        },
        {
            "account_name": "DinkinFlicka",
            "rank": 361,
            "top_hero_ids": [],
            "badge_level": null
        },
        {
            "account_name": "birdee",
            "rank": 361,
            "top_hero_ids": [],
            "badge_level": null
        },
        {
            "account_name": "helvetica",
            "rank": 363,
            "top_hero_ids": [],
            "badge_level": null
        },
        {
            "account_name": "skulcracka",
            "rank": 364,
            "top_hero_ids": [],
            "badge_level": null
        },
        {
            "account_name": "Jewish Wank",
            "rank": 365,
            "top_hero_ids": [],
            "badge_level": null
        },
        {
            "account_name": "GlizzyGlucker",
            "rank": 366,
            "top_hero_ids": [],
            "badge_level": null
        },
        {
            "account_name": "esans",
            "rank": 367,
            "top_hero_ids": [],
            "badge_level": null
        },
        {
            "account_name": "The Sly Turtle",
            "rank": 368,
            "top_hero_ids": [],
            "badge_level": null
        },
        {
            "account_name": "Bry",
            "rank": 369,
            "top_hero_ids": [],
            "badge_level": null
        },
        {
            "account_name": "Fuzzy2022",
            "rank": 370,
            "top_hero_ids": [],
            "badge_level": null
        },
        {
            "account_name": "P4nz3R | An\u00edbal",
            "rank": 371,
            "top_hero_ids": [],
            "badge_level": null
        },
        {
            "account_name": "InvyRain",
            "rank": 372,
            "top_hero_ids": [],
            "badge_level": null
        },
        {
            "account_name": "AKS",
            "rank": 373,
            "top_hero_ids": [],
            "badge_level": null
        },
        {
            "account_name": "Oreshnik",
            "rank": 373,
            "top_hero_ids": [],
            "badge_level": null
        },
        {
            "account_name": "LimeLicka",
            "rank": 375,
            "top_hero_ids": [],
            "badge_level": null
        },
        {
            "account_name": "r/BuddDwyer",
            "rank": 376,
            "top_hero_ids": [],
            "badge_level": null
        },
        {
            "account_name": "Spike11399",
            "rank": 377,
            "top_hero_ids": [],
            "badge_level": null
        },
        {
            "account_name": "Fang",
            "rank": 378,
            "top_hero_ids": [],
            "badge_level": null
        },
        {
            "account_name": "Tony",
            "rank": 379,
            "top_hero_ids": [],
            "badge_level": null
        },
        {
            "account_name": "110%CRAZY",
            "rank": 380,
            "top_hero_ids": [],
            "badge_level": null
        },
        {
            "account_name": "string bean",
            "rank": 380,
            "top_hero_ids": [],
            "badge_level": null
        },
        {
            "account_name": "B2b0mber",
            "rank": 382,
            "top_hero_ids": [],
            "badge_level": null
        },
        {
            "account_name": "Dubs",
            "rank": 383,
            "top_hero_ids": [],
            "badge_level": null
        },
        {
            "account_name": "Orphan Crippler",
            "rank": 384,
            "top_hero_ids": [],
            "badge_level": null
        },
        {
            "account_name": "Harold Zoid",
            "rank": 384,
            "top_hero_ids": [],
            "badge_level": null
        },
        {
            "account_name": "Gill",
            "rank": 386,
            "top_hero_ids": [],
            "badge_level": null
        },
        {
            "account_name": "EZwhiffs",
            "rank": 387,
            "top_hero_ids": [],
            "badge_level": null
        },
        {
            "account_name": "FreddyGas (MGE)",
            "rank": 388,
            "top_hero_ids": [],
            "badge_level": null
        },
        {
            "account_name": "algorhythm",
            "rank": 389,
            "top_hero_ids": [],
            "badge_level": null
        },
        {
            "account_name": "Yams",
            "rank": 390,
            "top_hero_ids": [],
            "badge_level": null
        },
        {
            "account_name": "Mesqx1",
            "rank": 391,
            "top_hero_ids": [],
            "badge_level": null
        },
        {
            "account_name": "W|LDHEART",
            "rank": 392,
            "top_hero_ids": [],
            "badge_level": null
        },
        {
            "account_name": "Matt Damon",
            "rank": 393,
            "top_hero_ids": [],
            "badge_level": null
        },
        {
            "account_name": "Liechie",
            "rank": 394,
            "top_hero_ids": [],
            "badge_level": null
        },
        {
            "account_name": "Dik McWiggletit",
            "rank": 395,
            "top_hero_ids": [],
            "badge_level": null
        },
        {
            "account_name": "ashieehehe",
            "rank": 396,
            "top_hero_ids": [],
            "badge_level": null
        },
        {
            "account_name": "ampers&",
            "rank": 397,
            "top_hero_ids": [],
            "badge_level": null
        },
        {
            "account_name": "Doogie Howser, M.D.",
            "rank": 398,
            "top_hero_ids": [],
            "badge_level": null
        },
        {
            "account_name": "Chesham",
            "rank": 399,
            "top_hero_ids": [],
            "badge_level": null
        },
        {
            "account_name": "Im3lunted",
            "rank": 399,
            "top_hero_ids": [],
            "badge_level": null
        },
        {
            "account_name": "Occult Coalition Agent",
            "rank": 401,
            "top_hero_ids": [],
            "badge_level": null
        },
        {
            "account_name": "Sydney",
            "rank": 401,
            "top_hero_ids": [],
            "badge_level": null
        },
        {
            "account_name": "SHIOtbt",
            "rank": 401,
            "top_hero_ids": [],
            "badge_level": null
        },
        {
            "account_name": "Heaviside",
            "rank": 404,
            "top_hero_ids": [],
            "badge_level": null
        },
        {
            "account_name": "SwoopDaLoop",
            "rank": 405,
            "top_hero_ids": [],
            "badge_level": null
        },
        {
            "account_name": "G A T R A B B I T ~",
            "rank": 405,
            "top_hero_ids": [],
            "badge_level": null
        },
        {
            "account_name": "noofin",
            "rank": 407,
            "top_hero_ids": [],
            "badge_level": null
        },
        {
            "account_name": "Space Cow Inc",
            "rank": 407,
            "top_hero_ids": [],
            "badge_level": null
        },
        {
            "account_name": "Xaltotun",
            "rank": 409,
            "top_hero_ids": [],
            "badge_level": null
        },
        {
            "account_name": "Oakum",
            "rank": 409,
            "top_hero_ids": [],
            "badge_level": null
        },
        {
            "account_name": "Loyco",
            "rank": 411,
            "top_hero_ids": [],
            "badge_level": null
        },
        {
            "account_name": "Monsters",
            "rank": 412,
            "top_hero_ids": [],
            "badge_level": null
        },
        {
            "account_name": "The Ghoul From Ipanema",
            "rank": 413,
            "top_hero_ids": [],
            "badge_level": null
        },
        {
            "account_name": "MtChemist",
            "rank": 413,
            "top_hero_ids": [],
            "badge_level": null
        },
        {
            "account_name": "JJ",
            "rank": 415,
            "top_hero_ids": [],
            "badge_level": null
        },
        {
            "account_name": "Quaaludes",
            "rank": 416,
            "top_hero_ids": [],
            "badge_level": null
        },
        {
            "account_name": "Phanfie",
            "rank": 417,
            "top_hero_ids": [],
            "badge_level": null
        },
        {
            "account_name": "Burnt898",
            "rank": 418,
            "top_hero_ids": [],
            "badge_level": null
        },
        {
            "account_name": "ToeGlazer",
            "rank": 419,
            "top_hero_ids": [],
            "badge_level": null
        },
        {
            "account_name": "d0a",
            "rank": 420,
            "top_hero_ids": [],
            "badge_level": null
        },
        {
            "account_name": "dookle",
            "rank": 421,
            "top_hero_ids": [],
            "badge_level": null
        },
        {
            "account_name": "The Honored Student",
            "rank": 421,
            "top_hero_ids": [],
            "badge_level": null
        },
        {
            "account_name": "Meatmaker",
            "rank": 423,
            "top_hero_ids": [],
            "badge_level": null
        },
        {
            "account_name": "CountCuckula",
            "rank": 424,
            "top_hero_ids": [],
            "badge_level": null
        },
        {
            "account_name": "oz",
            "rank": 424,
            "top_hero_ids": [],
            "badge_level": null
        },
        {
            "account_name": "compa",
            "rank": 426,
            "top_hero_ids": [],
            "badge_level": null
        },
        {
            "account_name": "PawsUneChatte",
            "rank": 426,
            "top_hero_ids": [],
            "badge_level": null
        },
        {
            "account_name": "SkyButterBen",
            "rank": 428,
            "top_hero_ids": [],
            "badge_level": null
        },
        {
            "account_name": "Penis Bender",
            "rank": 429,
            "top_hero_ids": [],
            "badge_level": null
        },
        {
            "account_name": "Mattimon",
            "rank": 430,
            "top_hero_ids": [],
            "badge_level": null
        },
        {
            "account_name": "Ramen Enema",
            "rank": 431,
            "top_hero_ids": [],
            "badge_level": null
        },
        {
            "account_name": "1br womb for rent(shared)",
            "rank": 432,
            "top_hero_ids": [],
            "badge_level": null
        },
        {
            "account_name": "Sm0ke",
            "rank": 433,
            "top_hero_ids": [],
            "badge_level": null
        },
        {
            "account_name": "HAG EROTIC",
            "rank": 434,
            "top_hero_ids": [],
            "badge_level": null
        },
        {
            "account_name": "Kbpanda",
            "rank": 435,
            "top_hero_ids": [],
            "badge_level": null
        },
        {
            "account_name": "InFest",
            "rank": 435,
            "top_hero_ids": [],
            "badge_level": null
        },
        {
            "account_name": "The Spanish Inquisition",
            "rank": 437,
            "top_hero_ids": [],
            "badge_level": null
        },
        {
            "account_name": "SwineFlu",
            "rank": 438,
            "top_hero_ids": [],
            "badge_level": null
        },
        {
            "account_name": "set",
            "rank": 439,
            "top_hero_ids": [],
            "badge_level": null
        },
        {
            "account_name": "SawBreath",
            "rank": 440,
            "top_hero_ids": [],
            "badge_level": null
        },
        {
            "account_name": "Genesis",
            "rank": 441,
            "top_hero_ids": [],
            "badge_level": null
        },
        {
            "account_name": "Nakedstone",
            "rank": 442,
            "top_hero_ids": [],
            "badge_level": null
        },
        {
            "account_name": "Dopeamine",
            "rank": 442,
            "top_hero_ids": [],
            "badge_level": null
        },
        {
            "account_name": "(\u274d\u1d25\u274d\u028b)\u0d9e",
            "rank": 442,
            "top_hero_ids": [],
            "badge_level": null
        },
        {
            "account_name": "Kancirous",
            "rank": 445,
            "top_hero_ids": [],
            "badge_level": null
        },
        {
            "account_name": "Snazzy",
            "rank": 445,
            "top_hero_ids": [],
            "badge_level": null
        },
        {
            "account_name": "Kavi",
            "rank": 447,
            "top_hero_ids": [],
            "badge_level": null
        },
        {
            "account_name": "Sleizer",
            "rank": 448,
            "top_hero_ids": [],
            "badge_level": null
        },
        {
            "account_name": "\u601c\u30cb\u30e3 - Reinya",
            "rank": 448,
            "top_hero_ids": [],
            "badge_level": null
        },
        {
            "account_name": "Teslaaa",
            "rank": 450,
            "top_hero_ids": [],
            "badge_level": null
        },
        {
            "account_name": "mr balls",
            "rank": 451,
            "top_hero_ids": [],
            "badge_level": null
        },
        {
            "account_name": "Madeline",
            "rank": 452,
            "top_hero_ids": [],
            "badge_level": null
        },
        {
            "account_name": "Skull Propheta",
            "rank": 452,
            "top_hero_ids": [],
            "badge_level": null
        },
        {
            "account_name": "Nobody",
            "rank": 454,
            "top_hero_ids": [],
            "badge_level": null
        },
        {
            "account_name": "Pickle",
            "rank": 455,
            "top_hero_ids": [],
            "badge_level": null
        },
        {
            "account_name": "Deathwish",
            "rank": 455,
            "top_hero_ids": [],
            "badge_level": null
        },
        {
            "account_name": "Solo_Cupid",
            "rank": 455,
            "top_hero_ids": [],
            "badge_level": null
        },
        {
            "account_name": "kamikazi",
            "rank": 458,
            "top_hero_ids": [],
            "badge_level": null
        },
        {
            "account_name": "Riscolso",
            "rank": 459,
            "top_hero_ids": [],
            "badge_level": null
        },
        {
            "account_name": "Natty Ice",
            "rank": 460,
            "top_hero_ids": [],
            "badge_level": null
        },
        {
            "account_name": "ONFIRE",
            "rank": 461,
            "top_hero_ids": [],
            "badge_level": null
        },
        {
            "account_name": "HoldmyC4",
            "rank": 462,
            "top_hero_ids": [],
            "badge_level": null
        },
        {
            "account_name": "DarthRizzian",
            "rank": 462,
            "top_hero_ids": [],
            "badge_level": null
        },
        {
            "account_name": "Luchador",
            "rank": 464,
            "top_hero_ids": [],
            "badge_level": null
        },
        {
            "account_name": "Fate-al-Error",
            "rank": 465,
            "top_hero_ids": [],
            "badge_level": null
        },
        {
            "account_name": "venicebitch",
            "rank": 466,
            "top_hero_ids": [],
            "badge_level": null
        },
        {
            "account_name": "Acelink",
            "rank": 467,
            "top_hero_ids": [],
            "badge_level": null
        },
        {
            "account_name": "Cutebrute",
            "rank": 468,
            "top_hero_ids": [],
            "badge_level": null
        },
        {
            "account_name": "dehydratedspinningbluepetercat",
            "rank": 468,
            "top_hero_ids": [],
            "badge_level": null
        },
        {
            "account_name": "Cytemi",
            "rank": 468,
            "top_hero_ids": [],
            "badge_level": null
        },
        {
            "account_name": "BLUEPOTATO",
            "rank": 471,
            "top_hero_ids": [],
            "badge_level": null
        },
        {
            "account_name": "Marcus Platinum",
            "rank": 472,
            "top_hero_ids": [],
            "badge_level": null
        },
        {
            "account_name": "goob",
            "rank": 473,
            "top_hero_ids": [],
            "badge_level": null
        },
        {
            "account_name": "Theos",
            "rank": 474,
            "top_hero_ids": [],
            "badge_level": null
        },
        {
            "account_name": "Miggy",
            "rank": 475,
            "top_hero_ids": [],
            "badge_level": null
        },
        {
            "account_name": "VlNV",
            "rank": 475,
            "top_hero_ids": [],
            "badge_level": null
        },
        {
            "account_name": "SnowLuna",
            "rank": 477,
            "top_hero_ids": [],
            "badge_level": null
        },
        {
            "account_name": "Phoenix Belle",
            "rank": 478,
            "top_hero_ids": [],
            "badge_level": null
        },
        {
            "account_name": "mbN Legend",
            "rank": 479,
            "top_hero_ids": [],
            "badge_level": null
        },
        {
            "account_name": "LiterallySoFree",
            "rank": 480,
            "top_hero_ids": [],
            "badge_level": null
        },
        {
            "account_name": "OverUsedTissue",
            "rank": 481,
            "top_hero_ids": [],
            "badge_level": null
        },
        {
            "account_name": "kyl",
            "rank": 482,
            "top_hero_ids": [],
            "badge_level": null
        },
        {
            "account_name": "smittywerbenjaegermanjensen",
            "rank": 482,
            "top_hero_ids": [],
            "badge_level": null
        },
        {
            "account_name": "Pulpopi",
            "rank": 484,
            "top_hero_ids": [],
            "badge_level": null
        },
        {
            "account_name": "eggdog",
            "rank": 485,
            "top_hero_ids": [],
            "badge_level": null
        },
        {
            "account_name": "Human Bean Juice",
            "rank": 486,
            "top_hero_ids": [],
            "badge_level": null
        },
        {
            "account_name": "duo q =",
            "rank": 487,
            "top_hero_ids": [],
            "badge_level": null
        },
        {
            "account_name": "laurencemartin41",
            "rank": 487,
            "top_hero_ids": [],
            "badge_level": null
        },
        {
            "account_name": "Blade: Trinity on Blu-Ray",
            "rank": 489,
            "top_hero_ids": [],
            "badge_level": null
        },
        {
            "account_name": "Smorphans",
            "rank": 489,
            "top_hero_ids": [],
            "badge_level": null
        },
        {
            "account_name": "JaxAsh",
            "rank": 489,
            "top_hero_ids": [],
            "badge_level": null
        },
        {
            "account_name": "Smawkee  \ud83d\udc3b",
            "rank": 492,
            "top_hero_ids": [],
            "badge_level": null
        },
        {
            "account_name": "Tsonu",
            "rank": 493,
            "top_hero_ids": [],
            "badge_level": null
        },
        {
            "account_name": "Put that in your pipe & smoke it",
            "rank": 493,
            "top_hero_ids": [],
            "badge_level": null
        },
        {
            "account_name": "PressX",
            "rank": 495,
            "top_hero_ids": [],
            "badge_level": null
        },
        {
            "account_name": "Ho Fo Sho",
            "rank": 496,
            "top_hero_ids": [],
            "badge_level": null
        },
        {
            "account_name": "NaggingNelly",
            "rank": 497,
            "top_hero_ids": [],
            "badge_level": null
        },
        {
            "account_name": "Brabadab",
            "rank": 498,
            "top_hero_ids": [],
            "badge_level": null
        },
        {
            "account_name": "Keelwa",
            "rank": 499,
            "top_hero_ids": [],
            "badge_level": null
        },
        {
            "account_name": "get out of the truck lil lady",
            "rank": 499,
            "top_hero_ids": [],
            "badge_level": null
        },
        {
            "account_name": "< blank >",
            "rank": 501,
            "top_hero_ids": [],
            "badge_level": null
        },
        {
            "account_name": "Big Borpa",
            "rank": 502,
            "top_hero_ids": [],
            "badge_level": null
        },
        {
            "account_name": "Lindil",
            "rank": 503,
            "top_hero_ids": [],
            "badge_level": null
        },
        {
            "account_name": "FlippyRobear",
            "rank": 504,
            "top_hero_ids": [],
            "badge_level": null
        },
        {
            "account_name": "Tytaku",
            "rank": 505,
            "top_hero_ids": [],
            "badge_level": null
        },
        {
            "account_name": "nakkamarra",
            "rank": 506,
            "top_hero_ids": [],
            "badge_level": null
        },
        {
            "account_name": "30k",
            "rank": 507,
            "top_hero_ids": [],
            "badge_level": null
        },
        {
            "account_name": "TwoToneTurtle",
            "rank": 507,
            "top_hero_ids": [],
            "badge_level": null
        },
        {
            "account_name": "Krum Bum",
            "rank": 509,
            "top_hero_ids": [],
            "badge_level": null
        },
        {
            "account_name": "Master Googway",
            "rank": 510,
            "top_hero_ids": [],
            "badge_level": null
        },
        {
            "account_name": "dirTy",
            "rank": 511,
            "top_hero_ids": [],
            "badge_level": null
        },
        {
            "account_name": "Jofai",
            "rank": 512,
            "top_hero_ids": [],
            "badge_level": null
        },
        {
            "account_name": "ThinkCreatively",
            "rank": 513,
            "top_hero_ids": [],
            "badge_level": null
        },
        {
            "account_name": "Michael Cera",
            "rank": 514,
            "top_hero_ids": [],
            "badge_level": null
        },
        {
            "account_name": "karsicc",
            "rank": 515,
            "top_hero_ids": [],
            "badge_level": null
        },
        {
            "account_name": "pilsnerboi",
            "rank": 516,
            "top_hero_ids": [],
            "badge_level": null
        },
        {
            "account_name": "Hunter",
            "rank": 516,
            "top_hero_ids": [],
            "badge_level": null
        },
        {
            "account_name": "crunkship",
            "rank": 518,
            "top_hero_ids": [],
            "badge_level": null
        },
        {
            "account_name": "elidibus",
            "rank": 518,
            "top_hero_ids": [],
            "badge_level": null
        },
        {
            "account_name": "Gato Borracho",
            "rank": 518,
            "top_hero_ids": [],
            "badge_level": null
        },
        {
            "account_name": "where are my skeletons",
            "rank": 518,
            "top_hero_ids": [],
            "badge_level": null
        },
        {
            "account_name": "Mr Mutz",
            "rank": 522,
            "top_hero_ids": [],
            "badge_level": null
        },
        {
            "account_name": "GnomelyFans",
            "rank": 523,
            "top_hero_ids": [],
            "badge_level": null
        },
        {
            "account_name": "A$AP Rocky Balboa Park",
            "rank": 524,
            "top_hero_ids": [],
            "badge_level": null
        },
        {
            "account_name": "meanrock",
            "rank": 525,
            "top_hero_ids": [],
            "badge_level": null
        },
        {
            "account_name": "Dirty Business",
            "rank": 526,
            "top_hero_ids": [],
            "badge_level": null
        },
        {
            "account_name": "trek97m",
            "rank": 527,
            "top_hero_ids": [],
            "badge_level": null
        },
        {
            "account_name": "Pillage",
            "rank": 528,
            "top_hero_ids": [],
            "badge_level": null
        },
        {
            "account_name": "Selendis",
            "rank": 528,
            "top_hero_ids": [],
            "badge_level": null
        },
        {
            "account_name": "Biggy Man!",
            "rank": 530,
            "top_hero_ids": [],
            "badge_level": null
        },
        {
            "account_name": "Saucy",
            "rank": 531,
            "top_hero_ids": [],
            "badge_level": null
        },
        {
            "account_name": "Deadlock Teammates All Suck",
            "rank": 532,
            "top_hero_ids": [],
            "badge_level": null
        },
        {
            "account_name": "Tet",
            "rank": 532,
            "top_hero_ids": [],
            "badge_level": null
        },
        {
            "account_name": "lizardking288",
            "rank": 534,
            "top_hero_ids": [],
            "badge_level": null
        },
        {
            "account_name": "Kipper",
            "rank": 534,
            "top_hero_ids": [],
            "badge_level": null
        },
        {
            "account_name": "shwzrd",
            "rank": 536,
            "top_hero_ids": [],
            "badge_level": null
        },
        {
            "account_name": "tastefactory",
            "rank": 537,
            "top_hero_ids": [],
            "badge_level": null
        },
        {
            "account_name": "Bloo Baby",
            "rank": 538,
            "top_hero_ids": [],
            "badge_level": null
        },
        {
            "account_name": "Aeternus",
            "rank": 539,
            "top_hero_ids": [],
            "badge_level": null
        },
        {
            "account_name": "knives",
            "rank": 540,
            "top_hero_ids": [],
            "badge_level": null
        },
        {
            "account_name": "Trileo",
            "rank": 541,
            "top_hero_ids": [],
            "badge_level": null
        },
        {
            "account_name": "GoodKingWood",
            "rank": 542,
            "top_hero_ids": [],
            "badge_level": null
        },
        {
            "account_name": "Switchell #RIPLittleBigPlanet",
            "rank": 543,
            "top_hero_ids": [],
            "badge_level": null
        },
        {
            "account_name": "Sven",
            "rank": 543,
            "top_hero_ids": [],
            "badge_level": null
        },
        {
            "account_name": "BeaksterTheGreat",
            "rank": 543,
            "top_hero_ids": [],
            "badge_level": null
        },
        {
            "account_name": "KeyLime [PIE]",
            "rank": 546,
            "top_hero_ids": [],
            "badge_level": null
        },
        {
            "account_name": "Mingosu",
            "rank": 547,
            "top_hero_ids": [],
            "badge_level": null
        },
        {
            "account_name": "KING AD",
            "rank": 548,
            "top_hero_ids": [],
            "badge_level": null
        },
        {
            "account_name": "Steve",
            "rank": 549,
            "top_hero_ids": [],
            "badge_level": null
        },
        {
            "account_name": "Tactical Cactus",
            "rank": 550,
            "top_hero_ids": [],
            "badge_level": null
        },
        {
            "account_name": "NTTGermania",
            "rank": 551,
            "top_hero_ids": [],
            "badge_level": null
        },
        {
            "account_name": "$ sudo rm -rf --no-preserve-root",
            "rank": 552,
            "top_hero_ids": [],
            "badge_level": null
        },
        {
            "account_name": "HelloKitty",
            "rank": 553,
            "top_hero_ids": [],
            "badge_level": null
        },
        {
            "account_name": "Baelryn",
            "rank": 554,
            "top_hero_ids": [],
            "badge_level": null
        },
        {
            "account_name": "Hammy",
            "rank": 555,
            "top_hero_ids": [],
            "badge_level": null
        },
        {
            "account_name": "NotAlvin",
            "rank": 556,
            "top_hero_ids": [],
            "badge_level": null
        },
        {
            "account_name": "MsDivine16",
            "rank": 557,
            "top_hero_ids": [],
            "badge_level": null
        },
        {
            "account_name": "Mr.DayQuan",
            "rank": 558,
            "top_hero_ids": [],
            "badge_level": null
        },
        {
            "account_name": "StinkyPeckPeckWoman",
            "rank": 559,
            "top_hero_ids": [],
            "badge_level": null
        },
        {
            "account_name": "thmsjfrsn",
            "rank": 560,
            "top_hero_ids": [],
            "badge_level": null
        },
        {
            "account_name": "ELF SCHIZO",
            "rank": 561,
            "top_hero_ids": [],
            "badge_level": null
        },
        {
            "account_name": "JAMES",
            "rank": 561,
            "top_hero_ids": [],
            "badge_level": null
        },
        {
            "account_name": "Sj",
            "rank": 563,
            "top_hero_ids": [],
            "badge_level": null
        },
        {
            "account_name": "proseeds",
            "rank": 564,
            "top_hero_ids": [],
            "badge_level": null
        },
        {
            "account_name": "Pe\u00e7anha",
            "rank": 565,
            "top_hero_ids": [],
            "badge_level": null
        },
        {
            "account_name": "\u1dbbzZ",
            "rank": 566,
            "top_hero_ids": [],
            "badge_level": null
        },
        {
            "account_name": "E.",
            "rank": 567,
            "top_hero_ids": [],
            "badge_level": null
        },
        {
            "account_name": "Iko\u0e51\ufb65",
            "rank": 568,
            "top_hero_ids": [],
            "badge_level": null
        },
        {
            "account_name": "Retleks",
            "rank": 569,
            "top_hero_ids": [],
            "badge_level": null
        },
        {
            "account_name": "Pavel",
            "rank": 570,
            "top_hero_ids": [],
            "badge_level": null
        },
        {
            "account_name": "Slayer",
            "rank": 571,
            "top_hero_ids": [],
            "badge_level": null
        },
        {
            "account_name": "SerLava",
            "rank": 572,
            "top_hero_ids": [],
            "badge_level": null
        },
        {
            "account_name": "Seeg",
            "rank": 573,
            "top_hero_ids": [],
            "badge_level": null
        },
        {
            "account_name": "runningtheclock",
            "rank": 574,
            "top_hero_ids": [],
            "badge_level": null
        },
        {
            "account_name": "Dent",
            "rank": 575,
            "top_hero_ids": [],
            "badge_level": null
        },
        {
            "account_name": "Salte",
            "rank": 576,
            "top_hero_ids": [],
            "badge_level": null
        },
        {
            "account_name": "DuncaNIdahO",
            "rank": 577,
            "top_hero_ids": [],
            "badge_level": null
        },
        {
            "account_name": "FUNEE MONKEE",
            "rank": 577,
            "top_hero_ids": [],
            "badge_level": null
        },
        {
            "account_name": "Hoshiko",
            "rank": 579,
            "top_hero_ids": [],
            "badge_level": null
        },
        {
            "account_name": "msm278",
            "rank": 580,
            "top_hero_ids": [],
            "badge_level": null
        },
        {
            "account_name": "The Don",
            "rank": 581,
            "top_hero_ids": [],
            "badge_level": null
        },
        {
            "account_name": "jaylee371319",
            "rank": 582,
            "top_hero_ids": [],
            "badge_level": null
        },
        {
            "account_name": "Lukeabrotz",
            "rank": 583,
            "top_hero_ids": [],
            "badge_level": null
        },
        {
            "account_name": "Corgano",
            "rank": 584,
            "top_hero_ids": [],
            "badge_level": null
        },
        {
            "account_name": "WheredNateGo",
            "rank": 585,
            "top_hero_ids": [],
            "badge_level": null
        },
        {
            "account_name": "Fstu",
            "rank": 586,
            "top_hero_ids": [],
            "badge_level": null
        },
        {
            "account_name": "Szabo666",
            "rank": 586,
            "top_hero_ids": [],
            "badge_level": null
        },
        {
            "account_name": "Almighty Cheezus",
            "rank": 588,
            "top_hero_ids": [],
            "badge_level": null
        },
        {
            "account_name": "kimbie",
            "rank": 589,
            "top_hero_ids": [],
            "badge_level": null
        },
        {
            "account_name": "Burger",
            "rank": 590,
            "top_hero_ids": [],
            "badge_level": null
        }
    ]
}